utf_table_generator/__init__.py
utf_table_generator/table.py
utf_table_generator-1.0.4.dist-info/METADATA
utf_table_generator-1.0.4.dist-info/WHEEL
utf_table_generator-1.0.4.dist-info/licenses/LICENSE
utf_table_generator-1.0.4.dist-info/RECORD
