Metadata-Version: 2.1
Name: utf_table_generator
Version: 1.0.4
Summary: Simple package that generates UTF-8 tables
Project-URL: Homepage, https://github.com/thecattest/utf-table-generator
Project-URL: Bug Tracker, https://github.com/thecattest/utf-table-generator/issues
Author-email: thecattest <vodopyanov999@gmail.com>
License-File: LICENSE
Classifier: License :: OSI Approved :: MIT License
Classifier: Operating System :: OS Independent
Classifier: Programming Language :: Python :: 3
Requires-Python: >=3.6
